README.md
setup.cfg
setup.py
src/k8s_netem/__init__.py
src/k8s_netem/impairment.py
src/k8s_netem/run.py
src/k8s_netem/webhook.py
src/k8s_netem.egg-info/PKG-INFO
src/k8s_netem.egg-info/SOURCES.txt
src/k8s_netem.egg-info/dependency_links.txt
src/k8s_netem.egg-info/entry_points.txt
src/k8s_netem.egg-info/requires.txt
src/k8s_netem.egg-info/top_level.txt