Metadata-Version: 1.0
Name: k8s-netem
Version: 0.1.0
Summary: Cross-pod network-emulation using Linux TC/netem for Kubernetes
Home-page: UNKNOWN
Author: UNKNOWN
Author-email: UNKNOWN
License: Apache 2.0
Keywords: netem,tc,network,kubernetes
Platform: UNKNOWN
